redison/__init__.py
redison/redis_object.py
redison-1.0a5.dist-info/METADATA
redison-1.0a5.dist-info/RECORD
redison-1.0a5.dist-info/WHEEL
redison-1.0a5.dist-info/top_level.txt
