Metadata-Version: 2.1
Name: redison
Version: 1.0a5
Summary: Shared memory object with redis and json files.
Home-page: https://github.com/JeanMaximilienCadic/redison
Author: Jean Maximilien Cadic
Author-email: j.cadic@9dw-lab.com
License: UNKNOWN
Platform: UNKNOWN
Classifier: Programming Language :: Python :: 3
Classifier: License :: OSI Approved :: MIT License
Classifier: Operating System :: OS Independent
Requires-Python: >=3
Requires-Dist: redis
Requires-Dist: gnutools-python
